Metadata-Version: 1.0
Name: django-graphql-framework
Version: 0.1.1
Summary: A simple, plug-and-play GraphQL library for Django
Home-page: https://github.com/jaydenwindle/django-graphql-framework/
Author: Jayden Windle
Author-email: jaydenwindle@gmail.com
License: MIT
Platform: UNKNOWN
